MANIFEST.in
README.txt
license.txt
setup.py
Django_Avocado.egg-info/PKG-INFO
Django_Avocado.egg-info/SOURCES.txt
Django_Avocado.egg-info/dependency_links.txt
Django_Avocado.egg-info/not-zip-safe
Django_Avocado.egg-info/requires.txt
Django_Avocado.egg-info/top_level.txt
avocado/__init__.py
avocado/admin.py
avocado/context.py
avocado/models.py
avocado/tests.py
avocado/urls.py
avocado/templates/avocado/details.html