Metadata-Version: 1.0
Name: Django-Avocado
Version: 0.2.0
Summary: Delicious delayed and cached database-logging for django.
Home-page: https://bitbucket.org/weholt/django-avocado
Author: Thomas Weholt
Author-email: thomas@weholt.org
License: GPL v.3
Keywords: cached logging database django
Platform: UNKNOWN
Classifier: Development Status :: 2 - Pre-Alpha
Classifier: Environment :: Web Environment
Classifier: Framework :: Django
Classifier: Intended Audience :: Developers
Classifier: License :: OSI Approved :: GNU General Public License (GPL)
Classifier: Operating System :: OS Independent
Classifier: Programming Language :: Python
Classifier: Topic :: Utilities
